hades/__init__.py
hades/core/__init__.py
hades/core/config.py
hades/core/executor.py
hades/core/model.py
hades/core/strategy.py
hades/core/backtesting/__init__.py
hades/core/backtesting/match.py
hades/core/backtesting/subscriber.py
hades/core/exchange/__init__.py
hades/core/exchange/binance_ex.py
hades/core/exchange/okx_ex.py
hades/core/messager/__init__.py
hades/core/messager/base.py
hades/core/messager/dingding.py
hades/core/messager/telegram.py
hades_core-0.0.4.dist-info/LICENSE
hades_core-0.0.4.dist-info/METADATA
hades_core-0.0.4.dist-info/WHEEL
hades_core-0.0.4.dist-info/top_level.txt
hades_core-0.0.4.dist-info/RECORD
