Metadata-Version: 2.1
Name: hades-core
Version: 0.0.4
Summary: cryptocurrency trading bot
Author-email: Gary Guo <gary.guo.china@gmail.com>
Maintainer-email: Gary Guo <gary.guo.china@gmail.com>
License: Apache License
Project-URL: Homepage, https://github.com/hades-trading/hades-core
Keywords: okx,binance,cryptocurrency
Classifier: Development Status :: 3 - Alpha
Classifier: Intended Audience :: Developers
Classifier: Topic :: Software Development :: Build Tools
Classifier: License :: OSI Approved :: MIT License
Classifier: Programming Language :: Python :: 3.9
Classifier: Programming Language :: Python :: 3.10
Classifier: Programming Language :: Python :: 3.11
Classifier: Programming Language :: Python :: 3 :: Only
Requires-Python: >=3.7
License-File: LICENSE
Requires-Dist: python-okx
Requires-Dist: websockets
Requires-Dist: requests
Requires-Dist: binance-futures-connector
Requires-Dist: python-telegram-bot
Requires-Dist: pydantic
